common_code/__init__.py
common_code/credentials.py
common_code/distribution/__init__.py
common_code/distribution/functions.py
common_code/distribution/sendFileToEos.py
common_code/metadata/reportTypeMap.json
itk_pdb_reportorium-0.1.14.dist-info/METADATA
itk_pdb_reportorium-0.1.14.dist-info/WHEEL
itk_pdb_reportorium-0.1.14.dist-info/top_level.txt
itk_pdb_reportorium-0.1.14.dist-info/RECORD
