Metadata-Version: 2.2
Name: itk-pdb-reportorium
Version: 0.1.14
Summary: A common repository for shared reporting tools for ITk PDB data:
Author: kenneth wraight, Omar Istaitia, Doyeong Kim, Dimitris Varouchas
Author-email: kenneth.wraight@glasgow.ac.uk, omar.istaitia@cern.ch, doyeong.kim@cern.ch, dimitris.varouchas@cern.ch
Requires-Dist: randomname
Requires-Dist: scp
Requires-Dist: paramiko
Dynamic: author
Dynamic: author-email
Dynamic: requires-dist
Dynamic: summary
